{
    "version": "5.5.0",
    "flags": {},
    "shapes": [
        {
            "label": "license",
            "points": [
                [
                    38.036269430051796,
                    11.854922279792746
                ],
                [
                    36.99999999999998,
                    64.70466321243524
                ],
                [
                    297.88082901554407,
                    63.927461139896366
                ],
                [
                    297.10362694300517,
                    8.746113989637294
                ]
            ],
            "group_id": null,
            "description": "",
            "shape_type": "polygon",
            "flags": {},
            "mask": null
        }
    ],
    "imagePath": "../IMG_6576_crop_0.jpg",
    "imageHeight": 82,
    "imageWidth": 324
}