{
    "version": "5.5.0",
    "flags": {},
    "shapes": [
        {
            "label": "license",
            "points": [
                [
                    27.601832993890017,
                    13.438900203665995
                ],
                [
                    28.009164969450097,
                    58.652749490835035
                ],
                [
                    236.1558044806517,
                    38.28615071283096
                ],
                [
                    232.36707081636115,
                    0.0
                ],
                [
                    164.6690427698574,
                    1.829938900203672
                ]
            ],
            "group_id": null,
            "description": "",
            "shape_type": "polygon",
            "flags": {},
            "mask": null
        }
    ],
    "imagePath": "../IMG_6463_crop_0.jpg",
    "imageHeight": 67,
    "imageWidth": 255
}