{
    "version": "5.5.0",
    "flags": {},
    "shapes": [
        {
            "label": "license",
            "points": [
                [
                    136.85039370078735,
                    56.56692913385828
                ],
                [
                    146.29921259842516,
                    216.40944881889766
                ],
                [
                    914.8031496062993,
                    426.6456692913386
                ],
                [
                    922.6771653543306,
                    254.99212598425197
                ]
            ],
            "group_id": null,
            "description": "",
            "shape_type": "polygon",
            "flags": {},
            "mask": null
        }
    ],
    "imagePath": "../IMG_4195_crop_0.jpg",
    "imageHeight": 484,
    "imageWidth": 980
}