{
    "version": "5.5.0",
    "flags": {},
    "shapes": [
        {
            "label": "license",
            "points": [
                [
                    15.112359550561791,
                    79.46441947565542
                ],
                [
                    26.348314606741567,
                    122.72284644194755
                ],
                [
                    145.2621722846442,
                    53.43445692883895
                ],
                [
                    134.5880149812734,
                    16.730337078651683
                ]
            ],
            "group_id": null,
            "description": "",
            "shape_type": "polygon",
            "flags": {},
            "mask": null
        }
    ],
    "imagePath": "../IMG_6582_crop_0.jpg",
    "imageHeight": 152,
    "imageWidth": 160
}