{
    "version": "5.5.0",
    "flags": {},
    "shapes": [
        {
            "label": "license",
            "points": [
                [
                    89.12738853503188,
                    44.73566878980891
                ],
                [
                    84.66878980891723,
                    167.0286624203822
                ],
                [
                    639.4458598726115,
                    191.23248407643314
                ],
                [
                    648.3630573248408,
                    78.49363057324841
                ]
            ],
            "group_id": null,
            "description": "",
            "shape_type": "polygon",
            "flags": {},
            "mask": null
        }
    ],
    "imagePath": "../IMG_6436_crop_0.jpg",
    "imageHeight": 271,
    "imageWidth": 798
}