{
    "version": "5.5.0",
    "flags": {},
    "shapes": [
        {
            "label": "license",
            "points": [
                [
                    157.47530864197537,
                    107.38271604938274
                ],
                [
                    153.77160493827168,
                    332.07407407407413
                ],
                [
                    1400.6851851851852,
                    301.20987654320993
                ],
                [
                    1396.9814814814815,
                    75.28395061728395
                ]
            ],
            "group_id": null,
            "description": "",
            "shape_type": "polygon",
            "flags": {},
            "mask": null
        }
    ],
    "imagePath": "../IMG_2996_crop_0.jpg",
    "imageHeight": 416,
    "imageWidth": 1531
}