{
    "version": "5.5.0",
    "flags": {},
    "shapes": [
        {
            "label": "license",
            "points": [
                [
                    74.22448979591839,
                    65.75510204081633
                ],
                [
                    50.75510204081634,
                    293.30612244897964
                ],
                [
                    1227.2857142857144,
                    445.3469387755101
                ],
                [
                    1245.6530612244899,
                    203.51020408163262
                ]
            ],
            "group_id": null,
            "description": "",
            "shape_type": "polygon",
            "flags": {},
            "mask": null
        }
    ],
    "imagePath": "../IMG_2769_crop_0.jpg",
    "imageHeight": 506,
    "imageWidth": 1276
}