{
    "version": "5.5.0",
    "flags": {},
    "shapes": [
        {
            "label": "license",
            "points": [
                [
                    78.8064516129032,
                    65.59677419354841
                ],
                [
                    86.54838709677418,
                    201.08064516129036
                ],
                [
                    730.4193548387096,
                    184.30645161290323
                ],
                [
                    738.8064516129032,
                    51.403225806451644
                ]
            ],
            "group_id": null,
            "description": "",
            "shape_type": "polygon",
            "flags": {},
            "mask": null
        }
    ],
    "imagePath": "../IMG_7009_crop_0.jpg",
    "imageHeight": 217,
    "imageWidth": 806
}