{
    "version": "5.5.0",
    "flags": {},
    "shapes": [
        {
            "label": "license",
            "points": [
                [
                    48.08791208791208,
                    71.69230769230768
                ],
                [
                    63.47252747252747,
                    300.26373626373623
                ],
                [
                    1316.2197802197802,
                    348.6153846153846
                ],
                [
                    1309.6263736263736,
                    115.64835164835165
                ]
            ],
            "group_id": null,
            "description": "",
            "shape_type": "polygon",
            "flags": {},
            "mask": null
        }
    ],
    "imagePath": "../IMG_2950_crop_0.jpg",
    "imageHeight": 428,
    "imageWidth": 1372
}