{
    "version": "5.5.0",
    "flags": {},
    "shapes": [
        {
            "label": "license",
            "points": [
                [
                    96.93708609271523,
                    51.20860927152319
                ],
                [
                    102.23509933774835,
                    183.658940397351
                ],
                [
                    711.5066225165564,
                    260.4801324503311
                ],
                [
                    714.1556291390729,
                    135.97682119205297
                ]
            ],
            "group_id": null,
            "description": "",
            "shape_type": "polygon",
            "flags": {},
            "mask": null
        }
    ],
    "imagePath": "../IMG_4219_crop_0.jpg",
    "imageHeight": 315,
    "imageWidth": 825
}