{
    "version": "5.5.0",
    "flags": {},
    "shapes": [
        {
            "label": "license",
            "points": [
                [
                    124.78260869565223,
                    99.10869565217394
                ],
                [
                    128.04347826086962,
                    318.67391304347825
                ],
                [
                    1191.0869565217392,
                    313.2391304347826
                ],
                [
                    1191.0869565217392,
                    95.84782608695656
                ]
            ],
            "group_id": null,
            "description": "",
            "shape_type": "polygon",
            "flags": {},
            "mask": null
        }
    ],
    "imagePath": "../IMG_3010_crop_0.jpg",
    "imageHeight": 458,
    "imageWidth": 1355
}