{
    "version": "5.5.0",
    "flags": {},
    "shapes": [
        {
            "label": "license",
            "points": [
                [
                    26.62499999999998,
                    8.970238095238088
                ],
                [
                    34.66071428571427,
                    64.02976190476191
                ],
                [
                    343.29166666666663,
                    56.29166666666667
                ],
                [
                    344.48214285714283,
                    3.31547619047619
                ]
            ],
            "group_id": null,
            "description": "",
            "shape_type": "polygon",
            "flags": {},
            "mask": null
        }
    ],
    "imagePath": "../IMG_6613_crop_0.jpg",
    "imageHeight": 73,
    "imageWidth": 372
}