{
    "version": "5.5.0",
    "flags": {},
    "shapes": [
        {
            "label": "license",
            "points": [
                [
                    14.249249249249246,
                    28.64264264264264
                ],
                [
                    14.999999999999996,
                    104.61861861861861
                ],
                [
                    160.04504504504504,
                    87.5015015015015
                ],
                [
                    157.4924924924925,
                    10.324324324324323
                ]
            ],
            "group_id": null,
            "description": "",
            "shape_type": "polygon",
            "flags": {},
            "mask": null
        }
    ],
    "imagePath": "../IMG_6553_crop_0.jpg",
    "imageHeight": 122,
    "imageWidth": 180
}