{
    "version": "5.5.0",
    "flags": {},
    "shapes": [
        {
            "label": "license",
            "points": [
                [
                    180.6538461538461,
                    88.43956043956047
                ],
                [
                    193.8406593406593,
                    306.021978021978
                ],
                [
                    1311.423076923077,
                    286.2417582417582
                ],
                [
                    1316.9175824175823,
                    71.95604395604397
                ]
            ],
            "group_id": null,
            "description": "",
            "shape_type": "polygon",
            "flags": {},
            "mask": null
        }
    ],
    "imagePath": "../IMG_3027_crop_0.jpg",
    "imageHeight": 356,
    "imageWidth": 1369
}