{
    "version": "5.5.0",
    "flags": {},
    "shapes": [
        {
            "label": "license",
            "points": [
                [
                    72.02684563758392,
                    62.36577181208054
                ],
                [
                    68.67114093959734,
                    207.3322147651007
                ],
                [
                    776.7248322147651,
                    220.08389261744966
                ],
                [
                    767.3288590604027,
                    71.76174496644296
                ]
            ],
            "group_id": null,
            "description": "",
            "shape_type": "polygon",
            "flags": {},
            "mask": null
        }
    ],
    "imagePath": "../IMG_7034_crop_0.jpg",
    "imageHeight": 265,
    "imageWidth": 836
}