{
    "version": "5.5.0",
    "flags": {},
    "shapes": [
        {
            "label": "license",
            "points": [
                [
                    58.92592592592597,
                    55.44444444444446
                ],
                [
                    67.81481481481485,
                    199.88888888888889
                ],
                [
                    825.5925925925926,
                    233.22222222222226
                ],
                [
                    821.8888888888889,
                    79.88888888888891
                ]
            ],
            "group_id": null,
            "description": "",
            "shape_type": "polygon",
            "flags": {},
            "mask": null
        }
    ],
    "imagePath": "../IMG_6451_crop_0.jpg",
    "imageHeight": 282,
    "imageWidth": 926
}